msbio/__init__.py
msbio/decoder.py
msbio/encoder.py
msbio/msbio.py
msbio_py-0.1.0.dist-info/LICENSE
msbio_py-0.1.0.dist-info/METADATA
msbio_py-0.1.0.dist-info/WHEEL
msbio_py-0.1.0.dist-info/RECORD
